[
    {
        "Date\n": "March 1960\n",
        "Mission success\n": "First solar probe.\n",
        "Country/organization\n": " USA (NASA)\n",
        "Mission name\n": "Pioneer 5\n",
        "Ref(s)\n": "\n"
    },
    {
        "Date\n": "19 August 1960\n",
        "Mission success\n": "First plants and animals to return alive from Earth orbit\n",
        "Country/organization\n": " USSR\n",
        "Mission name\n": "Sputnik 5\n",
        "Ref(s)\n": "\n"
    },
    {
        "Date\n": "10 October 1960\n",
        "Mission success\n": "First probe launched to Mars (failed to reach target)\n",
        "Country/organization\n": " USSR\n",
        "Mission name\n": "Mars 1M\n",
        "Ref(s)\n": "\n"
    },
    {
        "Date\n": "31 January 1961\n",
        "Mission success\n": "First Hominidae in space, first tasks performed in space; Ham (chimpanzee).\n",
        "Country/organization\n": " USA (NASA)\n",
        "Mission name\n": "M-R 2\n",
        "Ref(s)\n": "\n"
    },
    {
        "Date\n": "12 February 1961\n",
        "Mission success\n": "First launch from Earth orbit of upper stage into a heliocentric orbitFirst mid-course corrections First spin-stabilisation\n",
        "Country/organization\n": " USSR\n",
        "Mission name\n": "Venera 1\n",
        "Ref(s)\n": "\n"
    },
    {
        "Date\n": "12 April 1961\n",
        "Mission success\n": "First human spaceflight (Yuri Gagarin)First human-crewed orbital flight\n",
        "Country/organization\n": " USSR\n",
        "Mission name\n": "Vostok 1\n",
        "Ref(s)\n": "\n"
    },
    {
        "Date\n": "5 May 1961\n",
        "Mission success\n": "First human-piloted space flight (Alan Shepard)First human-crewed suborbital flightFirst human space mission that landed with pilot still in spacecraft, thus the first complete human spaceflight by FAI definitions.\n",
        "Country/organization\n": " USA\n",
        "Mission name\n": "Freedom 7\n",
        "Ref(s)\n": "[4]\n"
    },
    {
        "Date\n": "19 May 1961\n",
        "Mission success\n": "First planetary flyby (within 100,000 km of Venus – no data returned)\n",
        "Country/organization\n": " USSR\n",
        "Mission name\n": "Venera 1\n",
        "Ref(s)\n": "\n"
    },
    {
        "Date\n": "6 August 1961\n",
        "Mission success\n": "First crewed space flight lasting over twenty four hours by Gherman Titov, who is also the first to suffer from space sickness.\n",
        "Country/organization\n": " USSR\n",
        "Mission name\n": "Vostok 2\n",
        "Ref(s)\n": "\n"
    },
    {
        "Date\n": "7 March 1962\n",
        "Mission success\n": "First orbital solar observatory\n",
        "Country/organization\n": " USA (NASA)\n",
        "Mission name\n": "OSO-1\n",
        "Ref(s)\n": "\n"
    },
    {
        "Date\n": "26 April 1962\n",
        "Mission success\n": "First spacecraft to impact the far side of the Moon\n",
        "Country/organization\n": " USA (NASA)\n",
        "Mission name\n": "Ranger 4\n",
        "Ref(s)\n": "[5]\n"
    },
    {
        "Date\n": "11 August 1962\n",
        "Mission success\n": "First dual crewed spaceflightFirst communication between two crewed space vehicles in orbit.\n",
        "Country/organization\n": " USSR\n",
        "Mission name\n": "Vostok 3 & Vostok 4\n",
        "Ref(s)\n": "\n"
    },
    {
        "Date\n": "18 August 1962\n",
        "Mission success\n": "First auroral research rocket launched into the ionosphere\n",
        "Country/organization\n": " Norway\n",
        "Mission name\n": "Ferdinand 1\n",
        "Ref(s)\n": "\n"
    },
    {
        "Date\n": "November 1962\n",
        "Mission success\n": "First Mars flyby (11,000 km) but contact was lost\n",
        "Country/organization\n": " USSR\n",
        "Mission name\n": "Mars 1\n",
        "Ref(s)\n": "\n"
    },
    {
        "Date\n": "14 December 1962\n",
        "Mission success\n": "First successful planetary flyby (Venus closest approach 34,773 kilometers)\n",
        "Country/organization\n": " USA (NASA)\n",
        "Mission name\n": "Mariner 2\n",
        "Ref(s)\n": "\n"
    },
    {
        "Date\n": "16 June 1963\n",
        "Mission success\n": "First woman in space (Valentina Tereshkova)\n",
        "Country/organization\n": " USSR\n",
        "Mission name\n": "Vostok 6\n",
        "Ref(s)\n": "\n"
    },
    {
        "Date\n": "19 July 1963\n",
        "Mission success\n": "First reusable crewed spacecraft (suborbital)\n",
        "Country/organization\n": " USA (NASA)\n",
        "Mission name\n": "X-15 Flight 90\n",
        "Ref(s)\n": "\n"
    },
    {
        "Date\n": "12 October 1964\n",
        "Mission success\n": "First multi-person crew (3) in orbit\n",
        "Country/organization\n": " USSR\n",
        "Mission name\n": "Voskhod 1\n",
        "Ref(s)\n": "\n"
    },
    {
        "Date\n": "18 March 1965\n",
        "Mission success\n": "First space walk/extra-vehicular activity (Alexei Leonov)\n",
        "Country/organization\n": " USSR\n",
        "Mission name\n": "Voskhod 2\n",
        "Ref(s)\n": "\n"
    },
    {
        "Date\n": "March 1965\n",
        "Mission success\n": "First crewed spacecraft to change orbit\n",
        "Country/organization\n": " USA (NASA)\n",
        "Mission name\n": "Gemini 3\n",
        "Ref(s)\n": "\n"
    },
    {
        "Date\n": "14 July 1965\n",
        "Mission success\n": "First Mars flyby (closest approach 9,846 kilometers; returned pictures)\n",
        "Country/organization\n": " USA (NASA)\n",
        "Mission name\n": "Mariner 4\n",
        "Ref(s)\n": "\n"
    },
    {
        "Date\n": "14 July 1965\n",
        "Mission success\n": "First close-up photographs of another planet: Mars\n",
        "Country/organization\n": " USA (NASA)\n",
        "Mission name\n": "Mariner 4\n",
        "Ref(s)\n": "\n"
    },
    {
        "Date\n": "15 December 1965\n",
        "Mission success\n": "First orbital rendezvous (parallel flight, no docking)\n",
        "Country/organization\n": " USA (NASA)\n",
        "Mission name\n": "Gemini 6A/Gemini 7\n",
        "Ref(s)\n": "\n"
    },
    {
        "Date\n": "3 February 1966\n",
        "Mission success\n": "First soft landing on another world (the Moon) First photos from another world\n",
        "Country/organization\n": " USSR\n",
        "Mission name\n": "Luna 9\n",
        "Ref(s)\n": "\n"
    },
    {
        "Date\n": "1 March 1966\n",
        "Mission success\n": "First impact into another planet (Venus)\n",
        "Country/organization\n": " USSR\n",
        "Mission name\n": "Venera 3\n",
        "Ref(s)\n": "\n"
    },
    {
        "Date\n": "16 March 1966\n",
        "Mission success\n": "First orbital docking between two spacecraft\n",
        "Country/organization\n": " USA (NASA)\n",
        "Mission name\n": "Gemini 8/Agena target vehicle\n",
        "Ref(s)\n": "\n"
    },
    {
        "Date\n": "3 April 1966\n",
        "Mission success\n": "First artificial satellite around another world (the Moon)\n",
        "Country/organization\n": " USSR\n",
        "Mission name\n": "Luna 10\n",
        "Ref(s)\n": "\n"
    },
    {
        "Date\n": "August 1966\n",
        "Mission success\n": "First probe to map the Moon\n",
        "Country/organization\n": " USA\n",
        "Mission name\n": "Lunar Orbiter 1\n",
        "Ref(s)\n": "\n"
    },
    {
        "Date\n": "30 October 1967\n",
        "Mission success\n": "First automated (crewless) docking\n",
        "Country/organization\n": " USSR\n",
        "Mission name\n": "Cosmos 186/Cosmos 188\n",
        "Ref(s)\n": "\n"
    },
    {
        "Date\n": "September 1968\n",
        "Mission success\n": "First animals and plants to leave Earth orbit, to travel to and circle the Moon, and the first Moon mission with passengers to return safely to Earth\n",
        "Country/organization\n": " USSR\n",
        "Mission name\n": "Zond 5\n",
        "Ref(s)\n": "\n"
    },
    {
        "Date\n": "7 December 1968\n",
        "Mission success\n": "First orbital ultraviolet observatory\n",
        "Country/organization\n": " USA (NASA)\n",
        "Mission name\n": "OAO-2\n",
        "Ref(s)\n": "\n"
    },
    {
        "Date\n": "21 December 1968\n",
        "Mission success\n": "First piloted orbital mission of another celestial body (Moon),  First Trans-Earth injection First human space mission to enter the gravitational influence of another celestial body (25 December)\n",
        "Country/organization\n": " USA (NASA)\n",
        "Mission name\n": "Apollo 8\n",
        "Ref(s)\n": "\n"
    },
    {
        "Date\n": "January 1969\n",
        "Mission success\n": "First docking between two crewed spacecraft in Earth orbit, also the first crew exchange in space\n",
        "Country/organization\n": " USSR\n",
        "Mission name\n": "Soyuz 4 and Soyuz 5\n",
        "Ref(s)\n": "\n"
    },
    {
        "Date\n": "January 1969\n",
        "Mission success\n": "First to parachute in Venus's atmosphere, lost contact before landing.\n",
        "Country/organization\n": " USSR\n",
        "Mission name\n": "Venera 5\n",
        "Ref(s)\n": "\n"
    },
    {
        "Date\n": "23 May 1969\n",
        "Mission success\n": "First docking of two crewed spacecraft around another celestial body.\n",
        "Country/organization\n": " USA (NASA)\n",
        "Mission name\n": "Apollo 10\n",
        "Ref(s)\n": "\n"
    },
    {
        "Date\n": "20 July 1969\n",
        "Mission success\n": "First human on the Moon, and first space launch from a celestial body other than the EarthFirst sample return from the Moon.\n",
        "Country/organization\n": " USA (NASA)\n",
        "Mission name\n": "Apollo 11\n",
        "Ref(s)\n": "\n"
    },
    {
        "Date\n": "August 4, 1969\n",
        "Mission success\n": "First photograph of Phobos from Space\n",
        "Country/organization\n": " USA (NASA)\n",
        "Mission name\n": "Mariner 7\n",
        "Ref(s)\n": "\n"
    },
    {
        "Date\n": "19 November 1969\n",
        "Mission success\n": "First rendezvous on the surface of a celestial body\n",
        "Country/organization\n": " USA (NASA)\n",
        "Mission name\n": "Apollo 12/Surveyor 3\n",
        "Ref(s)\n": "\n"
    }
]